dbfread/__init__.py
dbfread/codepages.py
dbfread/dbf.py
dbfread/dbversions.py
dbfread/deprecated_dbf.py
dbfread/exceptions.py
dbfread/field_parser.py
dbfread/ifiles.py
dbfread/memo.py
dbfread/struct_parser.py
dbfread/test_field_parser.py
dbfread/test_ifiles.py
dbfread/test_invalid_value.py
dbfread/test_memo.py
dbfread/test_read_and_length.py
dbfread-2.0.6.dist-info/DESCRIPTION.rst
dbfread-2.0.6.dist-info/METADATA
dbfread-2.0.6.dist-info/RECORD
dbfread-2.0.6.dist-info/WHEEL
dbfread-2.0.6.dist-info/metadata.json
dbfread-2.0.6.dist-info/top_level.txt
dbfread-2.0.6.dist-info/zip-safe
